lazykey/__init__.py
lazykey/example.py
lazykey/key.py
lazykey/keyhandler.py
lazykey-0.0.2.dist-info/LICENSE
lazykey-0.0.2.dist-info/METADATA
lazykey-0.0.2.dist-info/WHEEL
lazykey-0.0.2.dist-info/top_level.txt
lazykey-0.0.2.dist-info/RECORD
