Metadata-Version: 2.2
Name: lazykey
Version: 0.0.2
Summary: Always uses the most lazy key when calling an online LLM.
Author-email: Nearchos Potamitis <nearchos.potamitis@cs.au.dk>
Project-URL: Homepage, https://github.com/Potamitisn/lazykey
Project-URL: Issues, https://github.com/Potamitisn/lazykey/issues
Classifier: Programming Language :: Python :: 3
Classifier: Operating System :: OS Independent
Classifier: License :: OSI Approved :: MIT License
Requires-Python: >=3.10
License-File: LICENSE
